pyworksio/__init__.py
pyworksio/mailer/__init__.py
pyworksio-0.1.0.dist-info/WHEEL
pyworksio-0.1.0.dist-info/METADATA
pyworksio-0.1.0.dist-info/RECORD
