Metadata-Version: 2.1
Name: pyworksio
Version: 0.1.0
Summary: PyWorks is an open source framework for fast-up web production.
Author: PyWorks Team
Requires-Python: >=3.7,<4.0
Classifier: Programming Language :: Python :: 3
Classifier: Programming Language :: Python :: 3.7
Classifier: Programming Language :: Python :: 3.8
Classifier: Programming Language :: Python :: 3.9
Requires-Dist: pyworks-mailer (==0.0.1rc2)
